client_sdk_python/__init__.py
client_sdk_python/admin.py
client_sdk_python/contract.py
client_sdk_python/datastructures.py
client_sdk_python/debug.py
client_sdk_python/error_code.py
client_sdk_python/eth.py
client_sdk_python/exceptions.py
client_sdk_python/fvnhash.py
client_sdk_python/iban.py
client_sdk_python/main.py
client_sdk_python/manager.py
client_sdk_python/miner.py
client_sdk_python/module.py
client_sdk_python/net.py
client_sdk_python/param_encode.py
client_sdk_python/parity.py
client_sdk_python/personal.py
client_sdk_python/pip.py
client_sdk_python/pm.py
client_sdk_python/ppos.py
client_sdk_python/rlpencode.py
client_sdk_python/shh.py
client_sdk_python/string2bytetest.py
client_sdk_python/testing.py
client_sdk_python/txpool.py
client_sdk_python/version.py
client_sdk_python/wasmcontract.py
client_sdk_python/auto/__init__.py
client_sdk_python/auto/gethdev.py
client_sdk_python/auto/http.py
client_sdk_python/auto/ipc.py
client_sdk_python/auto/websocket.py
client_sdk_python/auto/infura/__init__.py
client_sdk_python/auto/infura/endpoints.py
client_sdk_python/auto/infura/ropsten.py
client_sdk_python/gas_strategies/__init__.py
client_sdk_python/gas_strategies/rpc.py
client_sdk_python/gas_strategies/time_based.py
client_sdk_python/middleware/__init__.py
client_sdk_python/middleware/abi.py
client_sdk_python/middleware/attrdict.py
client_sdk_python/middleware/cache.py
client_sdk_python/middleware/exception_handling.py
client_sdk_python/middleware/exception_retry_request.py
client_sdk_python/middleware/fixture.py
client_sdk_python/middleware/formatting.py
client_sdk_python/middleware/gas_price_strategy.py
client_sdk_python/middleware/geth_poa.py
client_sdk_python/middleware/names.py
client_sdk_python/middleware/normalize_errors.py
client_sdk_python/middleware/normalize_request_parameters.py
client_sdk_python/middleware/pythonic.py
client_sdk_python/middleware/signing.py
client_sdk_python/middleware/simulate_unmined_transaction.py
client_sdk_python-1.1.1.dist-info/LICENSE
client_sdk_python-1.1.1.dist-info/METADATA
client_sdk_python-1.1.1.dist-info/WHEEL
client_sdk_python-1.1.1.dist-info/top_level.txt
client_sdk_python-1.1.1.dist-info/RECORD
